LICENSE
MANIFEST.in
README.md
requirements.txt
setup.py
ethraid/__init__.py
ethraid/cli.py
ethraid/driver.py
ethraid/helper_functions_astro.pyx
ethraid/helper_functions_general.pyx
ethraid/helper_functions_imaging.pyx
ethraid/helper_functions_plotting.py
ethraid/helper_functions_rv.pyx
ethraid/kern_profiler_dummy.py
ethraid/load_save.py
ethraid/plotter.py
ethraid.egg-info/PKG-INFO
ethraid.egg-info/SOURCES.txt
ethraid.egg-info/dependency_links.txt
ethraid.egg-info/entry_points.txt
ethraid.egg-info/requires.txt
ethraid.egg-info/top_level.txt
ethraid/c_kepler/__init__.py
ethraid/c_kepler/_kepler.c
ethraid/c_kepler/_kepler.pyx
ethraid/c_kepler/kepler.c
ethraid/c_kepler/radvel_requirements.txt
ethraid/c_kepler/radvel_setup.py
ethraid/compiled/_kepler.cpython-37m-darwin.so
ethraid/compiled/helper_functions_astro.cpython-37m-darwin.so
ethraid/compiled/helper_functions_general.cpython-37m-darwin.so
ethraid/compiled/helper_functions_imaging.cpython-37m-darwin.so
ethraid/compiled/helper_functions_rv.cpython-37m-darwin.so
ethraid/compiled/ethraid/helper_functions_astro.c
ethraid/compiled/ethraid/helper_functions_general.c
ethraid/compiled/ethraid/helper_functions_imaging.c
ethraid/compiled/ethraid/helper_functions_rv.c
ethraid/compiled/ethraid/c_kepler/_kepler.c
ethraid/compiled/ethraid/c_kepler/kepler.c
ethraid/data/.DS_Store
ethraid/data/TOI1694_832.csv
ethraid/data/bands.csv
ethraid/data/baraffe_table1.csv
ethraid/data/baraffe_table2.csv
ethraid/data/baraffe_table3.csv
ethraid/data/baraffe_table4.csv
ethraid/data/baraffe_table5.csv
ethraid/data/mamajek.csv
ethraid/data/test_K_band.csv
ethraid/data/test_K_band_altered.csv