Metadata-Version: 2.1
Name: ethraid
Version: 3.0
Summary: Characterize long-period companions using RV trends, astrometric accelerations, and direct imaging
Home-page: 
Author: Judah Van Zandt
Author-email: judahvz@astro.ucla.edu
License-File: LICENSE
